README.txt
setup.py
docs/HISTORY.txt
docs/INSTALL.txt
docs/LICENSE.GPL
docs/LICENSE.txt
experimental/__init__.py
experimental.collectionfix8463.egg-info/PKG-INFO
experimental.collectionfix8463.egg-info/SOURCES.txt
experimental.collectionfix8463.egg-info/dependency_links.txt
experimental.collectionfix8463.egg-info/entry_points.txt
experimental.collectionfix8463.egg-info/namespace_packages.txt
experimental.collectionfix8463.egg-info/not-zip-safe
experimental.collectionfix8463.egg-info/paster_plugins.txt
experimental.collectionfix8463.egg-info/requires.txt
experimental.collectionfix8463.egg-info/top_level.txt
experimental/collectionfix8463/__init__.py
experimental/collectionfix8463/configure.zcml
experimental/collectionfix8463/tests.py
experimental/collectionfix8463/Extensions/install.py
experimental/collectionfix8463/profiles/default_32/metadata.xml
experimental/collectionfix8463/profiles/default_32/skins.xml
experimental/collectionfix8463/profiles/default_33/metadata.xml
experimental/collectionfix8463/profiles/default_33/skins.xml
experimental/collectionfix8463/profiles/uninstall/skins.xml
experimental/collectionfix8463/skins/collectionfix8463_32/atct_album_view.pt
experimental/collectionfix8463/skins/collectionfix8463_32/atct_album_view.pt.metadata
experimental/collectionfix8463/skins/collectionfix8463_32/folder_listing.pt
experimental/collectionfix8463/skins/collectionfix8463_32/folder_listing.pt.metadata
experimental/collectionfix8463/skins/collectionfix8463_32/folder_summary_view.pt
experimental/collectionfix8463/skins/collectionfix8463_32/folder_summary_view.pt.metadata
experimental/collectionfix8463/skins/collectionfix8463_32/folder_tabular_view.pt
experimental/collectionfix8463/skins/collectionfix8463_32/folder_tabular_view.pt.metadata
experimental/collectionfix8463/skins/collectionfix8463_33/atct_album_view.pt
experimental/collectionfix8463/skins/collectionfix8463_33/atct_album_view.pt.metadata
experimental/collectionfix8463/skins/collectionfix8463_33/folder_listing.pt
experimental/collectionfix8463/skins/collectionfix8463_33/folder_listing.pt.metadata
experimental/collectionfix8463/skins/collectionfix8463_33/folder_summary_view.pt
experimental/collectionfix8463/skins/collectionfix8463_33/folder_summary_view.pt.metadata
experimental/collectionfix8463/skins/collectionfix8463_33/folder_tabular_view.pt
experimental/collectionfix8463/skins/collectionfix8463_33/folder_tabular_view.pt.metadata