Metadata-Version: 1.0
Name: experimental.collectionfix8463
Version: 0.2.0
Summary: A quick and dirty fix for the #8463 Plone issue with collections. Use only for versions before 3.3.6
Home-page: http://svn.plone.org/svn/collective/experimental.collectionfix8463
Author: RedTurtle Technology
Author-email: sviluppoplone@redturtle.net
License: GPL
Keywords: plone skins bug template collection
Platform: UNKNOWN
Classifier: Framework :: Plone
Classifier: Programming Language :: Python
